facialis_palsy_file_models/__init__.py
facialis_palsy_file_models/base_types.py
facialis_palsy_file_models/eface_type.py
facialis_palsy_file_models/housebrackmann_type.py
facialis_palsy_file_models/jauto_eface_file_type.py
facialis_palsy_file_models/sunnybrook_type.py
facialis_palsy_file_models/utils.py
facialis_palsy_file_models-0.1.0.data/scripts/facialis_file_parser.py
facialis_palsy_file_models-0.1.0.dist-info/LICENSE
facialis_palsy_file_models-0.1.0.dist-info/METADATA
facialis_palsy_file_models-0.1.0.dist-info/WHEEL
facialis_palsy_file_models-0.1.0.dist-info/top_level.txt
facialis_palsy_file_models-0.1.0.dist-info/RECORD
