Metadata-Version: 2.1
Name: facialis-palsy-file-models
Version: 0.1.0
Summary: Defining Facial Palsy Grading Models for eFACE, Sunnybrook, and House-Brackmann
Home-page: https://github.com/heinrich-foto/FacialPalsyFileModels
Author: Heinrich-Foto
Author-email: fnz@heinrich-foto.de
License: MIT
License-File: LICENSE
Requires-Dist: pydantic
Requires-Dist: click
